{"text": "The present study indicated that the formation of SCLC may be associated with cell cycle regulation. In addition, the four crucial genes CCNB1, CCNB2, MAD2L1 and CDK1, which are downstream of p53, may have important roles in the occurrence and progression of SCLC, and thus may be promising potential biomarkers and therapeutic targets.", "denotations": [{"id": "T1", "obj": "disease", "span": {"begin": 50, "end": 54}}, {"id": "T2", "obj": "gene", "span": {"begin": 137, "end": 142}}, {"id": "T3", "obj": "gene", "span": {"begin": 144, "end": 149}}, {"id": "T4", "obj": "gene", "span": {"begin": 151, "end": 157}}, {"id": "T5", "obj": "gene", "span": {"begin": 162, "end": 166}}, {"id": "T6", "obj": "gene", "span": {"begin": 192, "end": 195}}]}
